lucaone/__init__.py
lucaone/configuration_lucaone.py
lucaone/modeling_lucaone.py
lucaone/tokenization_lucaone.py
lucaone-1.1.1.dist-info/METADATA
lucaone-1.1.1.dist-info/WHEEL
lucaone-1.1.1.dist-info/top_level.txt
lucaone-1.1.1.dist-info/RECORD
